myDL/__init__.py
myDL/version.py
myDL/Fonts/kaiu.ttf
myDL/ts/GRU_attention.py
myDL/ts/GRU_attention_LR.py
myDL/ts/GRU_attention_cv.py
myDL/ts/GRU_attention_cv2.py
myDL/ts/__init__.py
myDL-0.0.20.dist-info/LICENSE
myDL-0.0.20.dist-info/METADATA
myDL-0.0.20.dist-info/WHEEL
myDL-0.0.20.dist-info/top_level.txt
myDL-0.0.20.dist-info/RECORD
