Metadata-Version: 2.1
Name: myDL
Version: 0.0.20
Summary: my deep learning
Home-page: https://github.com/jimmybow/myDL
Author: jimmybow
Author-email: jimmybow@hotmail.com.tw
License: BSD
Classifier: License :: OSI Approved :: BSD License
Classifier: Programming Language :: Python
Classifier: Programming Language :: Python :: 2.7
Classifier: Programming Language :: Python :: 3.3
Classifier: Programming Language :: Python :: 3.4
Classifier: Programming Language :: Python :: 3.5
Classifier: Programming Language :: Python :: 3.6
License-File: LICENSE
Requires-Dist: mydf
Requires-Dist: imageio
